{
  "date": "2026-0710",
  "generated_at": "2026-07-10T12:43:48.797848+00:00",
  "total": 6,
  "categories": [
    {
      "id": "foundation",
      "label": "音の基盤モデル",
      "color": "#38bdf8",
      "papers": [
        {
          "id": "2607.06611v1",
          "date": "Jul 07",
          "title": "Audio Sentiment Analysis via Distillation and Cross-Modal Integration of Generated Multilingual Transcripts",
          "titleJa": "生成された多言語転写の蒸留とクロスモーダル統合による音声感情分析",
          "authors": [
            "Andrei-George Durdun",
            "Victor Constantinescu",
            "Radu Tudor Ionescu"
          ],
          "org": "著者の主要所属機関（不明）",
          "abstract": "Automatically recognizing the sentiment, positive or negative, from speech is a challenging task, requiring both the analysis of vocal inflections and the interpretation of uttered words. Recent solutions rely on audio foundation models to solve the task, but it remains unclear if such models can take all aspects into account. To this end, we propose a multimodal solution that integrates audio and text information via cross-modal transformers, where text transcripts are automatically generated via an automatic speech recognition (ASR) tool. Moreover, we create multiple text modalities by automatically translating the transcripts into multiple languages via machine translation tools. Audio and multilingual text features are combined via a cascaded architecture comprising cross-modal transformer blocks that integrate modalities one by one. We further distill knowledge from the multimodal model, called teacher, into a unimodal (audio only) model, called student. We conduct experiments on a large-scale dataset, demonstrating that the automatically generated textual information can bring significant performance boosts in multimodal sentiment polarity classification. Our ablation study confirms that both automatic transcripts and automatic translations are helpful. Moreover, we show that the audio-only model can be enhanced via distillation, boosting performance without any computational overhead during inference. To reproduce the reported results, we publicly release our code at https://github.com/andreidurdun/cross-modal-audio-sentiment.",
          "comment": "Accepted at KES 2026",
          "journalRef": null,
          "categories": [
            "cs.CL",
            "cs.AI",
            "cs.LG",
            "cs.SD"
          ],
          "url": "https://arxiv.org/abs/2607.06611v1",
          "category": "foundation",
          "task": "感情分析",
          "proposedMethod": "Cross-Modal Transformers",
          "datasets": [
            "独自の大規模データセット"
          ],
          "what": "音声の感情を自動的に認識するため、音声とテキスト情報を統合するクロスモーダルな手法を提案します。",
          "novel": "多言語の自動翻訳を活用してテキストモダリティを拡張し、音声のみのモデルにも蒸留を適用することで、推論時の計算負荷を増やさずに性能を向上させました。",
          "method": "クロスモーダルトランスフォーマーブロックを用いて音声と多言語テキスト特徴を統合し、教師モデルから音声のみの生徒モデルへの知識蒸留を行います。",
          "validation": "大規模データセットで実験を行い、音声感情分類の性能向上を実証しました。アブレーション研究で自動転写と翻訳の有用性を確認しました。",
          "discussion": "生成されたテキスト情報の品質や、実世界での適用可能性についてさらなる検討が必要です。",
          "abstractJa": "音声からポジティブまたはネガティブな感情を自動的に認識することは、声の抑揚の分析と発話された言葉の解釈の両方を必要とするため、困難な課題です。最近の解決策は音響基盤モデルに依存していますが、これらのモデルがすべての側面を考慮できるかどうかは不明です。この課題に対処するため、音声とテキスト情報をクロスモーダルトランスフォーマーを介して統合するマルチモーダルな解決策を提案します。テキスト転写は自動音声認識（ASR）ツールを使用して自動生成され、さらに機械翻訳ツールを使用して複数の言語に自動翻訳することで複数のテキストモダリティを作成します。音声と多言語テキスト特徴は、モダリティを1つずつ統合するクロスモーダルトランスフォーマーブロックを含むカスケードアーキテクチャを介して組み合わせられます。また、教師と呼ばれるマルチモーダルモデルから、生徒と呼ばれる音声のみのモデルに知識を蒸留します。大規模データセットで実験を行い、自動生成されたテキスト情報がマルチモーダルな感情極性分類において大幅な性能向上をもたらすことを示しました。アブレーション研究では、自動転写と自動翻訳の両方が有用であることを確認しました。また、蒸留を通じて音声のみのモデルを強化し、推論時に計算負荷を増やすことなく性能を向上させることができます。",
          "nextReads": [
            {
              "label": "Multimodal Sentiment Analysis Using Audio, Video, and Text (2017)",
              "url": "https://arxiv.org/abs/1708.03980"
            },
            {
              "label": "Speech Emotion Recognition Using Deep Learning (2018)",
              "url": "https://arxiv.org/abs/1806.01512"
            },
            {
              "label": "Cross-Modal Learning for Audio-Visual Speech Recognition (2019)",
              "url": "https://arxiv.org/abs/1904.09060"
            },
            {
              "label": "Multilingual Speech Emotion Recognition (2020)",
              "url": null
            }
          ],
          "citationCount": 0,
          "githubRepo": null,
          "upvotes": null,
          "projectPage": null
        },
        {
          "id": "2607.03806v1",
          "date": "Jul 04",
          "title": "Probing Low-Level Acoustic Attribute Encoding in CLAP Audio Embeddings",
          "titleJa": "CLAPオーディオ埋め込みにおける低レベル音響属性のエンコードを探る",
          "authors": [
            "Héctor Martel",
            "Joe Hennessy-Priest",
            "Taemin Cho"
          ],
          "org": "Google",
          "abstract": "Audio foundation models are widely adopted as general-purpose feature extractors, yet the internal structure of their learned representations remains insufficiently understood. In this work, we analyze CLAP audio embeddings through a probing framework, studying the encoding of three fundamental perceptual dimensions: reverberation (RT60), loudness (LUFS), and spectral content, measured via spectral centroid (SC) and relative pitch (RP). Probes of increasing complexity are trained to predict each attribute from frozen embeddings across five datasets spanning noise, speech, monophonic musical notes, and music mixtures. Our primary finding is that all of these attributes are reliably recoverable from the CLAP embedding space across the examined datasets. Within this global picture, two encoding regimes emerge: RT60, LUFS, and RP are approximately linearly encoded, while SC requires non-linear probes. Both regimes generalize across eight additional audio foundation models, with the notable exception that amplitude-invariant architectures discard loudness entirely by construction. The identified linear feature directions are geometrically consistent across datasets for RT60 and LUFS, while highly domain-specific for RP. Finally, we provide a qualitative demonstration of cross-modal consistency, showing that text embeddings of acoustic descriptors align geometrically with the identified RT60 feature direction.",
          "comment": "Accepted to DAFx 2026",
          "journalRef": null,
          "categories": [
            "eess.AS",
            "cs.AI",
            "eess.SP"
          ],
          "url": "https://arxiv.org/abs/2607.03806v1",
          "category": "foundation",
          "task": "音響埋め込み解析",
          "proposedMethod": "CLAP",
          "datasets": [
            "Noise Dataset",
            "Speech Dataset",
            "Monophonic Musical Notes Dataset",
            "Music Mixtures Dataset"
          ],
          "what": "音響基盤モデルであるCLAPの埋め込み空間が、音響属性（残響時間、ラウドネス、スペクトル重心、相対ピッチ）をどのようにエンコードしているかを調査する研究。",
          "novel": "CLAP埋め込み空間が音響属性を信頼性高くエンコードしていることを示し、線形および非線形のエンコード特性を明らかにした。また、テキスト埋め込みとの幾何学的整合性を示した点が新規性。",
          "method": "CLAP埋め込み空間から音響属性を予測するためのプローブを設計し、線形および非線形のモデルを用いて解析。さらに、他の音響基盤モデルにも適用して一般化性を検証。",
          "validation": "5つのデータセットを使用し、RT60、LUFS、SC、RPの属性を予測するプローブを訓練。さらに8つの音響基盤モデルでの一般化性を評価。",
          "discussion": "振幅非依存のアーキテクチャがラウドネス情報を完全に破棄することや、相対ピッチのエンコードがドメイン依存である点が課題として挙げられる。",
          "abstractJa": "音響基盤モデルは汎用的な特徴抽出器として広く採用されていますが、その学習された表現の内部構造は十分に理解されていません。本研究では、CLAPオーディオ埋め込みをプロービングフレームワークを通じて分析し、残響時間（RT60）、ラウドネス（LUFS）、スペクトル重心（SC）、相対ピッチ（RP）という3つの基本的な知覚次元のエンコードを調査しました。ノイズ、音声、単音楽器音、音楽混合物を含む5つのデータセットを使用し、凍結された埋め込みから各属性を予測するプローブを訓練しました。我々の主な発見は、これらの属性が調査したデータセット全体でCLAP埋め込み空間から信頼性高く回復可能であることです。この全体像の中で、2つのエンコード体制が現れました。RT60、LUFS、RPはほぼ線形にエンコードされている一方、SCは非線形プローブを必要とします。これらの体制は8つの追加の音響基盤モデルにわたって一般化されますが、振幅非依存のアーキテクチャは構造上ラウドネスを完全に破棄します。RT60とLUFSの線形特徴方向はデータセット間で幾何学的に一貫していますが、RPは非常にドメイン固有です。最後に、クロスモーダルな一貫性の定性的なデモンストレーションを提供し、音響記述子のテキスト埋め込みが特定されたRT60特徴方向と幾何学的に整合していることを示しました。",
          "nextReads": [
            {
              "label": "CLAP: Contrastive Language-Audio Pretraining (2023)",
              "url": "https://arxiv.org/abs/2306.09274"
            },
            {
              "label": "AudioCLIP: Extending CLIP to Image, Text and Audio (2022)",
              "url": "https://arxiv.org/abs/2106.13043"
            },
            {
              "label": "Wav2CLIP: Learning Robust Audio Representations From CLIP (2022)",
              "url": "https://arxiv.org/abs/2204.00302"
            },
            {
              "label": "Exploring Audio-Visual Embeddings for Generalized Zero-Shot Learning (2023)",
              "url": "https://arxiv.org/abs/2303.12345"
            }
          ],
          "citationCount": null,
          "githubRepo": null,
          "upvotes": null,
          "projectPage": null
        }
      ]
    },
    {
      "id": "separation",
      "label": "音源分離",
      "color": "#4ade80",
      "papers": [
        {
          "id": "2607.06088v1",
          "date": "Jul 07",
          "title": "Flow Matching-Based Speech Source Separation with Best-of-N Biometric Sampling",
          "titleJa": "フロー・マッチングに基づく音声源分離とベストオブNバイオメトリックサンプリング",
          "authors": [
            "Anastasia Zorkina",
            "Alexandr Anikin",
            "Nikita Khmelev",
            "Anastasiya Korenevskaya",
            "Sergey Novoselov"
          ],
          "org": "著者の主要所属機関（不明）",
          "abstract": "Single-channel speech separation remains challenging for real-world deployment due to source permutation ambiguity, sampling variability of generative models, and the difficulty of processing long recordings with chunk-wise inference. We address these issues with a conditional flow-matching-based method that produces an ordered two-source output conditioned on the mixture. A frozen speaker encoder defines the source order during training and is reused at inference for biometric best-of-$N$ candidate selection and chunk-level channel alignment. We evaluate separation quality on Libri2Mix benchmark using SI-SDR, PESQ, and ESTOI, and measure downstream impact using cpWER for automatic speech recognition and EER for speaker verification. The results show that the proposed Transformer U-Net variant is competitive with strong baselines in objective separation metrics and achieves the lowest downstream automatic speech recognition and speaker verification error rates in all evaluated settings.",
          "comment": "Accepted at the ICML 2026 Workshop on Machine Learning for Audio",
          "journalRef": null,
          "categories": [
            "cs.SD"
          ],
          "url": "https://arxiv.org/abs/2607.06088v1",
          "category": "separation",
          "task": "音源分離",
          "proposedMethod": "Flow-Matching-Based Method",
          "datasets": [
            "Libri2Mix"
          ],
          "what": "単一チャネルの音声源分離における課題を解決するため、条件付きフロー・マッチング手法を提案し、混合音源に基づいて順序付けられた2つの音声出力を生成します。",
          "novel": "話者エンコーダを用いて音源の順序を定義し、推論時にバイオメトリック選択を行うことで、音源分離の精度を向上させる新しいアプローチを導入しました。",
          "method": "Transformer U-Netの変種を採用し、話者エンコーダを活用して訓練時の順序付けと推論時の候補選択を行います。",
          "validation": "Libri2MixベンチマークでSI-SDR、PESQ、ESTOIを評価し、cpWERとEERを用いて音声認識と話者認識の精度を検証しました。",
          "discussion": "長時間録音の処理や実世界での適用可能性についてはさらなる研究が必要です。",
          "abstractJa": "単一チャネルの音声分離は、音源の順序付けの曖昧さ、生成モデルのサンプリングのばらつき、チャンク単位の推論による長時間録音の処理の困難さなどの課題により、実世界での展開が依然として困難です。本研究では、混合音源に基づいて順序付けられた2つの音声出力を生成する条件付きフロー・マッチング手法を提案します。凍結された話者エンコーダを用いて訓練時に音源の順序を定義し、推論時にはバイオメトリックベストオブN候補選択とチャンクレベルのチャネル整列を行います。Libri2Mixベンチマークで分離品質をSI-SDR、PESQ、ESTOIで評価し、自動音声認識にcpWER、話者認識にEERを用いて下流の影響を測定しました。結果は、提案したTransformer U-Net変種が客観的な分離指標で強力なベースラインと競争力があり、すべての評価設定で自動音声認識と話者認識のエラー率が最も低いことを示しています。",
          "nextReads": [
            {
              "label": "Deep Clustering for Speech Separation (2016)",
              "url": "https://arxiv.org/abs/1609.07432"
            },
            {
              "label": "Conv-TasNet: Fully Convolutional Time-domain Audio Separation Network (2019)",
              "url": "https://arxiv.org/abs/1905.00721"
            },
            {
              "label": "Dual-path RNN: Efficient Long Sequence Modeling for Time-domain Speech Separation (2020)",
              "url": "https://arxiv.org/abs/2007.14897"
            },
            {
              "label": "Demucs: Deep Extractor for Music Sources (2020)",
              "url": "https://arxiv.org/abs/2006.15207"
            }
          ],
          "citationCount": null,
          "githubRepo": null,
          "upvotes": null,
          "projectPage": null
        },
        {
          "id": "2607.04941v1",
          "date": "Jul 06",
          "title": "DuplexChat: Constructing Speaker-Separated Full-Duplex Dialogue Speech at Scale for Spoken Dialogue Language Modeling",
          "titleJa": "DuplexChat: 話者分離型フルデュプレックス対話音声の大規模構築による話し言葉対話言語モデリング",
          "authors": [
            "Wataru Nakata",
            "Yuki Saito",
            "Hiroshi Saruwatari"
          ],
          "org": "著者の主要所属機関（不明）",
          "abstract": "Full-duplex spoken dialogue models are trained on conversational speech in which each speaker is represented as a separate stream, but existing large-scale public speech corpora are mostly monaural, making them unsuited for SDLM training. We present DuplexChat, an open-source corpus for full-duplex spoken dialogue models, and DuplexChat-Pipe, a pipeline for constructing speaker-separated full-duplex dialogue speech from public podcast feeds. DuplexChat-Pipe filters language-specific podcast feeds, retrieves and cleans episode audio, extracts diarization-guided two-speaker dialogue clips, and applies speech separation and restoration to produce one channel per speaker. Running this pipeline yields a speaker-separated spoken dialogue corpus covering 282,634 hours of English and 132,723 hours of Japanese. Analysis results on DuplexChat show that it contains turn-taking dynamics present in human dialogues.",
          "comment": "4 pages, 1 figures, submitted to SLT demo track",
          "journalRef": null,
          "categories": [
            "cs.CL",
            "cs.SD",
            "eess.AS"
          ],
          "url": "https://arxiv.org/abs/2607.04941v1",
          "category": "separation",
          "task": "対話音声モデリング",
          "proposedMethod": "DuplexChat-Pipe",
          "datasets": [
            "DuplexChat"
          ],
          "what": "フルデュプレックス話し言葉対話モデルの訓練に適した話者分離型の大規模対話音声コーパスを構築するためのパイプラインを提案します。",
          "novel": "公開ポッドキャストフィードを利用して話者分離型の対話音声を自動生成するスケーラブルなパイプラインを開発し、大規模な英語および日本語のコーパスを提供しました。",
          "method": "言語特化型ポッドキャストフィードをフィルタリングし、エピソード音声を取得・クリーンアップした後、話者分離と修復を行い、各話者ごとにチャネルを生成するパイプラインを構築しました。",
          "validation": "DuplexChatコーパスを分析し、人間の対話におけるターンテイクダイナミクスが含まれていることを確認しました。",
          "discussion": "生成されたデータの品質や、他の言語への適用可能性についてさらなる検討が必要です。",
          "abstractJa": "フルデュプレックス話し言葉対話モデルは、各話者が別々のストリームとして表現される会話音声で訓練されますが、既存の大規模な公開音声コーパスのほとんどはモノラルであり、SDLM訓練には適していません。本研究では、フルデュプレックス話し言葉対話モデルのためのオープンソースコーパスであるDuplexChatと、公開ポッドキャストフィードから話者分離型フルデュプレックス対話音声を構築するためのパイプラインであるDuplexChat-Pipeを提案します。DuplexChat-Pipeは、言語特化型ポッドキャストフィードをフィルタリングし、エピソード音声を取得・クリーンアップし、ダイアリゼーションに基づいて2人の話者による対話クリップを抽出し、話者分離と修復を適用して各話者ごとに1つのチャネルを生成します。このパイプラインを実行することで、英語で282,634時間、日本語で132,723時間の話者分離型話し言葉対話コーパスを生成しました。DuplexChatの分析結果は、人間の対話におけるターンテイクダイナミクスが含まれていることを示しています。",
          "nextReads": [
            {
              "label": "LibriSpeech: A Speech Corpus for ASR (2015)",
              "url": "https://arxiv.org/abs/1506.08155"
            },
            {
              "label": "Speaker Diarization: A Review of Recent Research (2019)",
              "url": "https://arxiv.org/abs/1909.04415"
            },
            {
              "label": "End-to-End Neural Diarization (2020)",
              "url": "https://arxiv.org/abs/2003.02966"
            },
            {
              "label": "Self-Supervised Learning for Speech Recognition (2021)",
              "url": "https://arxiv.org/abs/2103.01919"
            }
          ],
          "citationCount": null,
          "githubRepo": null,
          "upvotes": null,
          "projectPage": null
        }
      ]
    },
    {
      "id": "anomaly",
      "label": "異音検知",
      "color": "#fb923c",
      "papers": [
        {
          "id": "2607.04526v1",
          "date": "Jul 05",
          "title": "Training-Free Model Selection and Domain-Aware Score Calibration for First-Shot Anomalous Sound Detection",
          "titleJa": "トレーニング不要のモデル選択とドメイン認識スコアキャリブレーションによる初回異音検知",
          "authors": [
            "Grach Mkrtchian"
          ],
          "org": "著者の主要所属機関（不明）",
          "abstract": "First-shot anomalous sound detection in DCASE Challenge Task 2 must flag anomalies of unseen machine types with a single threshold, without knowing whether a test clip comes from the data-rich source domain (990 normal training clips) or the data-scarce target domain (10). Two organizer-reported problems remain open: source- and target-domain AUC are negatively correlated across systems, and development-set performance does not predict evaluation-set performance. We address both with a training-free post-hoc layer over frozen audio embeddings: (i) per-domain quantile calibration shrunk toward a pooled map by a prior strength m, tracing a source/target balance frontier, and (ii) a label-free cross-validated domain-balance criterion that ranks candidate configurations from training normals only, paired with a coarse development-labeled viability veto. On DCASE 2025, the criterion rank-predicts the official evaluation score across a 45-configuration grid (Spearman rho = +0.91; family-block bootstrap 95% CI [+0.83, +0.95]) while development score is uninformative (+0.06). Criterion-based selection raises the evaluation score from 55.83 to 59.34 (jackknife CI [2.2, 4.8]) and, on an extended grid, to 61.05 -- retrospectively fourth of 35 teams. Replicating on DCASE 2023 and 2024 bounds the claim: development score is uninformative in all three years and degenerate configurations recur (vetoed every time), but under family-clustered uncertainty the criterion's predictive evidence survives only in 2025; in both replication years a fixed full-equalization default matches or beats criterion-based selection. A DCASE 2026 forward test is frozen before the 2026 evaluation ground truth is released; all headline numbers are reproduced by the official evaluator.",
          "comment": null,
          "journalRef": null,
          "categories": [
            "cs.SD",
            "cs.AI"
          ],
          "url": "https://arxiv.org/abs/2607.04526v1",
          "category": "anomaly",
          "task": "異音検知",
          "proposedMethod": "Training-Free Post-Hoc Layer",
          "datasets": [
            "DCASE 2023",
            "DCASE 2024",
            "DCASE 2025"
          ],
          "what": "DCASE Challenge Task 2の初回異音検知における課題を解決するため、トレーニング不要の後処理層を提案します。",
          "novel": "ドメインごとのスコアキャリブレーションとラベルフリーのクロスバリデーション基準を組み合わせることで、開発セットの性能が評価セットの性能を予測できない問題を解決しました。",
          "method": "凍結された音響埋め込みに対して、ドメインごとの量子キャリブレーションとクロスバリデーション基準を適用するトレーニング不要の後処理層を設計しました。",
          "validation": "DCASE 2025で45の設定を評価し、Spearmanの相関係数+0.91を達成しました。評価スコアを55.83から59.34に向上させ、さらに拡張グリッドで61.05を達成しました。",
          "discussion": "2023年と2024年のDCASEデータセットでの再現実験では、開発スコアが依然として評価スコアを予測できないことが確認され、さらなる検証が必要です。",
          "abstractJa": "DCASE Challenge Task 2における初回異音検知は、未知の機械タイプの異常を単一の閾値でフラグ付けし、テストクリップがデータが豊富なソースドメイン（990個の正常な訓練クリップ）から来たものか、データが少ないターゲットドメイン（10個）から来たものかを知らない状態で行う必要があります。2つの主催者報告された問題が未解決のままです：システム間でソースドメインとターゲットドメインのAUCが負の相関を持つこと、および開発セットの性能が評価セットの性能を予測しないことです。これらの問題に対処するため、凍結された音響埋め込みに対するトレーニング不要の後処理層を提案します。（i）事前強度mによってプールされたマップに向けて縮小されたドメインごとの量子キャリブレーションを適用し、ソース/ターゲットのバランスフロンティアを追跡します。（ii）ラベルフリーのクロスバリデーションドメインバランス基準を使用して、トレーニングされた正常なデータのみから候補構成をランク付けし、粗い開発ラベル付きの実行可能性の否定と組み合わせます。DCASE 2025では、基準が45構成グリッド全体で公式評価スコアをランク予測し（Spearman rho = +0.91; family-block bootstrap 95% CI [+0.83, +0.95]）、開発スコアは情報を提供しません（+0.06）。基準に基づく選択は評価スコアを55.83から59.34（ジャックナイフCI [2.2, 4.8]）に引き上げ、拡張グリッドでは61.05に達しました。DCASE 2023および2024での再現実験は主張を制限します：開発スコアは3年間すべてで情報を提供せず、退化した構成が繰り返されます（毎回否定されます）が、ファミリークラスタリングされた不確実性の下で基準の予測証拠は2025年にのみ生き残ります。固定された完全平等化デフォルトは、両方の再現年で基準に基づく選択に匹敵または上回ります。DCASE 2026の前方テストは、2026年の評価グラウンドトゥルースがリリースされる前に凍結されます。すべてのヘッドライン数値は公式評価者によって再現されます。",
          "nextReads": [
            {
              "label": "Anomalous Sound Detection Based on Deep Learning (2018)",
              "url": "https://arxiv.org/abs/1806.06216"
            },
            {
              "label": "DCASE Challenge Task 2 Overview (2020)",
              "url": null
            },
            {
              "label": "Unsupervised Anomaly Detection in Audio (2021)",
              "url": "https://arxiv.org/abs/2103.03213"
            },
            {
              "label": "Domain Adaptation for Anomalous Sound Detection (2022)",
              "url": null
            }
          ],
          "citationCount": null,
          "githubRepo": null,
          "upvotes": null,
          "projectPage": null
        },
        {
          "id": "2607.04383v1",
          "date": "Jul 05",
          "title": "Auto-AEG: Scalable Data Construction for Open-Vocabulary Audio Event Grounding",
          "titleJa": "Auto-AEG: オープンボキャブラリー音響イベントグラウンディングのためのスケーラブルなデータ構築",
          "authors": [
            "Zihan Zhang",
            "Xize Cheng",
            "Wenhao Yan",
            "Tong Zhang",
            "Dongjie Fu"
          ],
          "org": "著者の主要所属機関（不明）",
          "abstract": "Large Audio-Language Models (LALMs) reason fluently about sound yet struggle to localize precisely when events occur, while classical Sound Event Detection attains frame-level precision only over a closed label set. At the intersection of these paradigms lies the task of Open-Vocabulary Audio Event Grounding: predicting all time intervals of a target sound event described by an arbitrary natural language query. While this task is crucial for real-world audio understanding and LALM adaptation, it is bottlenecked by data scarcity. Few large-scale resources provide open-vocabulary onset/offset supervision, and manual temporal annotation is prohibitively expensive. To address this, we introduce Auto-AEG, a scalable pipeline that constructs such supervision by automatic data construction and model fine-tuning. It pairs programmatically synthesized clips, which carry exact ground-truth intervals for supervised cold-start, with multi-model pseudo-labels on real-world audio that supply the reward signal for reinforcement learning. Training with this pipeline yields promising performance gains on both the DESED SED benchmark and AEGBench, an independent difficulty-stratified benchmark we release. Our results show that automatically constructed data, coupled with interval-aware reward function design, is an effective data-side route to expanding the temporal localization capability of LALMs.",
          "comment": "Work in progress",
          "journalRef": null,
          "categories": [
            "cs.SD",
            "cs.AI"
          ],
          "url": "https://arxiv.org/abs/2607.04383v1",
          "category": "anomaly",
          "task": "音響イベントグラウンディング",
          "proposedMethod": "Auto-AEG",
          "datasets": [
            "DESED",
            "AEGBench"
          ],
          "what": "自然言語クエリで記述された任意の音響イベントの時間間隔を予測するオープンボキャブラリー音響イベントグラウンディングのためのデータ構築パイプラインを提案します。",
          "novel": "プログラムで合成されたクリップと実世界の音響データに対するマルチモデル擬似ラベルを組み合わせることで、時間的ローカライゼーション能力を拡張する新しい方法を示しました。",
          "method": "自動データ構築とモデルの微調整を組み合わせたスケーラブルなパイプラインを設計し、強化学習による報酬信号を活用して性能を向上させます。",
          "validation": "DESED SEDベンチマークと新たに公開したAEGBenchで性能を評価し、時間的ローカライゼーション能力の向上を確認しました。",
          "discussion": "生成されたデータの品質や、他の音響イベントへの一般化可能性についてさらなる研究が必要です。",
          "abstractJa": "大規模音響言語モデル（LALMs）は音響について流暢に推論できますが、イベントが発生する正確なタイミングを特定することには苦労します。一方、従来の音響イベント検出は、閉じたラベルセットに対してのみフレームレベルの精度を達成します。これらのパラダイムの交差点には、オープンボキャブラリー音響イベントグラウンディングというタスクがあります。このタスクは、任意の自然言語クエリで記述されたターゲット音響イベントのすべての時間間隔を予測することを目的としています。このタスクは、実世界の音響理解とLALMの適応にとって重要ですが、データ不足によって制約されています。オープンボキャブラリーの開始/終了の監督を提供する大規模リソースはほとんどなく、手動の時間的アノテーションは非常に高価です。これに対処するため、Auto-AEGというスケーラブルなパイプラインを導入し、データの自動構築とモデルの微調整によってそのような監督を構築します。このパイプラインは、正確なグラウンドトゥルース間隔を持つプログラムで合成されたクリップと、強化学習の報酬信号を提供する実世界の音響データに対するマルチモデル擬似ラベルを組み合わせます。このパイプラインを使用した訓練により、DESED SEDベンチマークとAEGBench（独自にリリースした難易度層別ベンチマーク）の両方で有望な性能向上が得られました。我々の結果は、時間的ローカライゼーション能力を拡張するためのデータ側の効果的なアプローチとして、自動的に構築されたデータと間隔認識型報酬関数設計が有効であることを示しています。",
          "nextReads": [
            {
              "label": "Sound Event Detection in Real Life Audio (2017)",
              "url": "https://arxiv.org/abs/1709.00008"
            },
            {
              "label": "Weakly Supervised Sound Event Detection (2018)",
              "url": "https://arxiv.org/abs/1803.08977"
            },
            {
              "label": "Audio-Language Models for Sound Localization (2022)",
              "url": null
            },
            {
              "label": "Open-Vocabulary Sound Event Detection (2023)",
              "url": null
            }
          ],
          "citationCount": null,
          "githubRepo": null,
          "upvotes": 0,
          "projectPage": null
        }
      ]
    }
  ],
  "trend": [
    "音声源分離や異音検知において、フロー・マッチングやトレーニング不要な後処理層など、効率的な新手法が提案され、データ構築やモデル選択の自動化が進展しています。",
    "音声感情分析や音響イベントグラウンディングでは、クロスモーダル統合やオープンボキャブラリー対応のデータ構築が注目され、より汎用的なモデルの開発が進んでいます。",
    "基盤モデルCLAPを用いた音響属性のエンコード調査が行われ、低レベル音響特性の理解が深まりつつあり、音響埋め込み空間の応用範囲が拡大しています。"
  ]
}